compass/__init__.py
compass/_version.py
compass/exceptions.py
compass/pb.py
compass/warn.py
compass/_cli/__init__.py
compass/_cli/finalize.py
compass/_cli/main.py
compass/_cli/process.py
compass/common/__init__.py
compass/common/base.py
compass/common/tree.py
compass/data/conus_jurisdictions.csv
compass/extraction/__init__.py
compass/extraction/apply.py
compass/extraction/date.py
compass/extraction/features.py
compass/extraction/small_wind/__init__.py
compass/extraction/small_wind/graphs.py
compass/extraction/small_wind/ordinance.py
compass/extraction/small_wind/parse.py
compass/extraction/solar/__init__.py
compass/extraction/solar/graphs.py
compass/extraction/solar/ordinance.py
compass/extraction/solar/parse.py
compass/extraction/wind/__init__.py
compass/extraction/wind/graphs.py
compass/extraction/wind/ordinance.py
compass/extraction/wind/parse.py
compass/llm/__init__.py
compass/llm/calling.py
compass/llm/config.py
compass/scripts/__init__.py
compass/scripts/download.py
compass/scripts/process.py
compass/services/__init__.py
compass/services/base.py
compass/services/cpu.py
compass/services/openai.py
compass/services/provider.py
compass/services/queues.py
compass/services/threaded.py
compass/services/usage.py
compass/utilities/__init__.py
compass/utilities/base.py
compass/utilities/enums.py
compass/utilities/finalize.py
compass/utilities/io.py
compass/utilities/jurisdictions.py
compass/utilities/location.py
compass/utilities/logs.py
compass/utilities/ngrams.py
compass/utilities/nt.py
compass/utilities/parsing.py
compass/validation/__init__.py
compass/validation/content.py
compass/validation/graphs.py
compass/validation/location.py
compass/web/__init__.py
compass/web/website_crawl.py
nrel_compass-0.12.0.dist-info/licenses/LICENSE
nrel_compass-0.12.0.dist-info/METADATA
nrel_compass-0.12.0.dist-info/WHEEL
nrel_compass-0.12.0.dist-info/entry_points.txt
nrel_compass-0.12.0.dist-info/top_level.txt
nrel_compass-0.12.0.dist-info/RECORD
