Metadata-Version: 2.4
Name: NREL-COMPASS
Version: 0.12.0
Summary: INFRA-COMPASS is a tool that leverages Large Language Models (LLMs) to create and maintain an inventory of state and local codes and ordinances applicable to energy infrastructure.
Author-email: Paul Pinchuk <ppinchuk@nrel.gov>, Guilherme Castelão <gpimenta@nrel.gov>
Maintainer-email: Paul Pinchuk <ppinchuk@nrel.gov>, Guilherme Castelão <gpimenta@nrel.gov>
License-Expression: BSD-3-Clause
Project-URL: homepage, https://github.com/NREL/COMPASS
Project-URL: documentation, https://nrel.github.io/COMPASS/
Project-URL: repository, https://github.com/NREL/COMPASS
Keywords: COMPASS,NLR,Ordinance,Database
Classifier: Development Status :: 4 - Beta
Classifier: Intended Audience :: Science/Research
Classifier: Natural Language :: English
Classifier: Operating System :: OS Independent
Classifier: Programming Language :: Python :: 3
Classifier: Programming Language :: Python :: 3.12
Classifier: Programming Language :: Python :: 3.13
Classifier: Topic :: Software Development :: Libraries :: Application Frameworks
Requires-Python: >=3.12
License-File: LICENSE
Requires-Dist: beautifulsoup4<5,>=4.12.3
Requires-Dist: click<9,>=8.1.7
Requires-Dist: html5lib<2,>=1.1
Requires-Dist: langchain-text-splitters<2,>=1.0.0
Requires-Dist: networkx<4,>=3.4.2
Requires-Dist: nltk<4,>=3.9.1
Requires-Dist: nrel-elm<1,>=0.0.34
Requires-Dist: numpy<3,>=2.2.4
Requires-Dist: openai>=1.1.0
Requires-Dist: pandas<3,>=2.2.3
Requires-Dist: pdftotext<3,>=2.2.2
Requires-Dist: playwright<1.52,>=1.49.0
Requires-Dist: pyjson5<3,>=2.0.0
Requires-Dist: rich<14,>=13.9.4
Provides-Extra: ocr
Requires-Dist: pytesseract<0.4,>=0.3.13; extra == "ocr"
Provides-Extra: dev
Requires-Dist: jupyter<1.1,>=1.0.0; extra == "dev"
Requires-Dist: pipreqs<0.5,>=0.4.13; extra == "dev"
Requires-Dist: ruff<0.15,>=0.14.11; extra == "dev"
Requires-Dist: ruff-lsp<0.0.63,>=0.0.62; extra == "dev"
Provides-Extra: test
Requires-Dist: flaky<4,>=3.8.1; extra == "test"
Requires-Dist: pytest<9,>=8.3.3; extra == "test"
Requires-Dist: pytest-asyncio<0.26,>=0.25.2; extra == "test"
Requires-Dist: pytest-cases<4,>=3.8.6; extra == "test"
Requires-Dist: pytest-cov<7,>=6.0.0; extra == "test"
Requires-Dist: pytest-mock<4,>=3.14.0; extra == "test"
Requires-Dist: pytest-profiling<2,>=1.7.0; extra == "test"
Requires-Dist: pytest-xdist<4,>=3.6.1; extra == "test"
Requires-Dist: snakeviz<3,>=2.2.2; extra == "test"
Requires-Dist: tox<5,>=4.23.2; extra == "test"
Provides-Extra: doc
Requires-Dist: ghp-import<3,>=2.1.0; extra == "doc"
Requires-Dist: pydata-sphinx-theme<0.17,>=0.16.1; extra == "doc"
Requires-Dist: sphinx-click<7,>=6.1.0; extra == "doc"
Requires-Dist: sphinx-copybutton>=0.5; extra == "doc"
Requires-Dist: sphinx-tabs>=3.4; extra == "doc"
Requires-Dist: sphinxcontrib-mermaid<2,>=1.2.3; extra == "doc"
Provides-Extra: anthropic
Requires-Dist: anthropic<0.41,>=0.40.0; extra == "anthropic"
Requires-Dist: botocore<2,>=1.35.72; extra == "anthropic"
Requires-Dist: boto3<2,>=1.35.71; extra == "anthropic"
Provides-Extra: build
Requires-Dist: build<2,>=1.2.2; extra == "build"
Requires-Dist: pkginfo<2,>=1.12.1.2; extra == "build"
Requires-Dist: twine<7,>=6.1.0; extra == "build"
Dynamic: license-file
